changeset/__init__.py
changeset/__main__.py
changeset/changelog.py
changeset/changeset.py
changeset/check_changeset.py
changeset/validate_changesets.py
changeset/version.py
changeset-0.2.8.dist-info/METADATA
changeset-0.2.8.dist-info/WHEEL
changeset-0.2.8.dist-info/entry_points.txt
changeset-0.2.8.dist-info/licenses/LICENSE
changeset-0.2.8.dist-info/RECORD
