Metadata-Version: 2.4
Name: changeset
Version: 0.2.8
Summary: Changeset management tool for Python projects
Project-URL: Homepage, https://github.com/the-roaring/pychangeset
Project-URL: Repository, https://github.com/the-roaring/pychangeset
Project-URL: Issues, https://github.com/the-roaring/pychangeset/issues
Author-email: Roaring Knight <knight@purelymail.com>
License: MIT
License-File: LICENSE
Keywords: changelog,changeset,release,versioning
Classifier: Development Status :: 3 - Alpha
Classifier: Intended Audience :: Developers
Classifier: License :: OSI Approved :: MIT License
Classifier: Programming Language :: Python :: 3
Classifier: Programming Language :: Python :: 3.13
Classifier: Topic :: Software Development :: Build Tools
Classifier: Topic :: Software Development :: Version Control
Requires-Python: >=3.13
Requires-Dist: click>=8.0
Requires-Dist: coolname>=2.0
Requires-Dist: gitpython>=3.0
Requires-Dist: packaging>=21.0
Requires-Dist: questionary>=2.1.0
Requires-Dist: rich>=10.0
Requires-Dist: toml>=0.10
